zdatasets/__init__.py
zdatasets/_typing.py
zdatasets/context.py
zdatasets/dataset_plugin.py
zdatasets/datasets_decorator.py
zdatasets/exceptions.py
zdatasets/metaflow.py
zdatasets/mode.py
zdatasets/plugins/__init__.py
zdatasets/plugins/batch/__init__.py
zdatasets/plugins/batch/batch_base_plugin.py
zdatasets/plugins/batch/batch_dataset.py
zdatasets/plugins/batch/flow_dataset.py
zdatasets/plugins/batch/hive_dataset.py
zdatasets/plugins/executors/__init__.py
zdatasets/plugins/executors/metaflow_executor.py
zdatasets/plugins/register_plugins.py
zdatasets/program_executor.py
zdatasets/tests/__init__.py
zdatasets/tests/conftest.py
zdatasets/tests/data/train/date=2020-07-23/region=king/data.parquet
zdatasets/tests/data/train/date=2020-07-23/region=la/data.parquet
zdatasets/tests/test_batch_dataset.py
zdatasets/tests/test_dataset_plugin.py
zdatasets/tests/test_datasets_decorator.py
zdatasets/tests/test_flow_dataset.py
zdatasets/tests/test_hive_dataset.py
zdatasets/tests/test_metaflow.py
zdatasets/tests/test_tutorials.py
zdatasets/tests/utils/__init__.py
zdatasets/tests/utils/test_case_utils.py
zdatasets/tests/utils/test_partitions.py
zdatasets/tests/utils/test_secret_fetcher.py
zdatasets/tutorials/0_hello_dataset_flow.py
zdatasets/tutorials/1_input_output_flow.py
zdatasets/tutorials/2_spark_dask_flow.py
zdatasets/tutorials/3_foreach_dataset_flow.py
zdatasets/tutorials/4_hello_plugin_flow.py
zdatasets/tutorials/5_consistent_flow.py
zdatasets/tutorials/6_hive_dataset_flow.py
zdatasets/tutorials/README.ipynb
zdatasets/tutorials/online_plugin.py
zdatasets/utils/__init__.py
zdatasets/utils/aws.py
zdatasets/utils/case_utils.py
zdatasets/utils/partitions.py
zdatasets/utils/secret_fetcher.py
zdatasets-1.2.5.dist-info/LICENSE
zdatasets-1.2.5.dist-info/METADATA
zdatasets-1.2.5.dist-info/WHEEL
zdatasets-1.2.5.dist-info/entry_points.txt
zdatasets-1.2.5.dist-info/RECORD
