Metadata-Version: 2.1
Name: zdatasets
Version: 1.2.5
Summary: Dataset SDK for consistent read/write [batch, online, streaming] data.
Author: Taleb Zeghmi
Requires-Python: >=3.8.0,<4
Classifier: Development Status :: 2 - Pre-Alpha
Classifier: Intended Audience :: Developers
Classifier: License :: OSI Approved :: Apache Software License
Classifier: Natural Language :: English
Classifier: Programming Language :: Python :: 3
Classifier: Programming Language :: Python :: 3.8
Classifier: Programming Language :: Python :: 3.9
Classifier: Programming Language :: Python :: 3.10
Classifier: Programming Language :: Python :: 3.11
Provides-Extra: dask
Provides-Extra: doc
Provides-Extra: kubernetes
Provides-Extra: metaflow
Provides-Extra: spark
Requires-Dist: click (>=7.0,<8.1)
Requires-Dist: dask (>=2021.9.1) ; extra == "dask"
Requires-Dist: importlib-metadata (>=4.6.1)
Requires-Dist: kubernetes (>=12.0.0) ; extra == "kubernetes"
Requires-Dist: pandas (>=1.1.0)
Requires-Dist: pyarrow (>=6.0.0)
Requires-Dist: pyspark (>=3.2.0,<4.0.0) ; extra == "spark"
Requires-Dist: s3fs (>=2022.1.0)
Requires-Dist: tenacity (>=5.0)
